pyCoreWLAN/CWChannel.pyi
pyCoreWLAN/CWConfiguration.pyi
pyCoreWLAN/CWInterface.pyi
pyCoreWLAN/CWNetwork.pyi
pyCoreWLAN/CWNetworkProfile.pyi
pyCoreWLAN/CWWiFiClient.pyi
pyCoreWLAN/CoreWLAN.pyi
pyCoreWLAN/CoreWLANConstants.pyi
pyCoreWLAN/CoreWLANTypes.pyi
pyCoreWLAN/CoreWLANUtil.pyi
pyCoreWLAN/FoundationTypes.pyi
pyCoreWLAN/__init__.py
pyCoreWLAN-1.0.1.dist-info/LICENSE.txt
pyCoreWLAN-1.0.1.dist-info/METADATA
pyCoreWLAN-1.0.1.dist-info/WHEEL
pyCoreWLAN-1.0.1.dist-info/top_level.txt
pyCoreWLAN-1.0.1.dist-info/RECORD
