Metadata-Version: 2.1
Name: pyCoreWLAN
Version: 1.0.1
Summary: A Python package that provides stubs for the PyObjC CoreWLAN Wrapper.
Home-page: https://github.com/lawsonoates/pyCoreWLAN
Author: Lawson Oates
Project-URL: Bug Tracker, https://github.com/lawsonoates/pyCoreWLAN/issues
Project-URL: repository, https://github.com/lawsonoates/pyCoreWLAN
Classifier: Programming Language :: Python :: 3
Classifier: License :: OSI Approved :: MIT License
Classifier: Operating System :: OS Independent
Requires-Python: >=3.6
License-File: LICENSE.txt
